{"Arcanum Worlds; Odyssey of the Dragonlords.json":{"n":["Odyssey of the Dragonlords"],"a":["OotD"],"s":"wip","e":0},"Ghostfire Gaming; Dungeons of Drakkenheim In Search of the Smuggler's Secrets.json":{"n":["Dungeons of Drakkenheim: In Search of the Smuggler's Secrets"],"a":["ISotSS"],"p":1,"e":1},"Kobold Press; Book of Lairs.json":{"n":["Book of Lairs"],"a":["BoL"],"e":0},"Kobold Press; Tome of Beasts 2 Lairs.json":{"n":["Tome of Beasts 2 Lairs"],"a":["ToB2"],"e":0},"Kobold Press; Tome of Beasts 3 Lairs.json":{"n":["Tome of Beasts 3 Lairs"],"a":["ToB3"],"e":0},"MonkeyDM; Heresy of Steel - A Steinhardt's Adventure.json":{"n":["Steinhardt's Guide to the Eldritch Hunt: Heresy of Steel"],"a":["SGttEH:HoS"],"e":0},"zeek0; Backgrounds Omnibus.json":{"n":["Backgrounds Omnibus"],"a":["BGO"],"e":0},"enders; Oversized Longbow.json":{"n":["Generic Oversized Longbow"],"a":["WDH-GOL"],"e":0},"aeyana; The Book of Hordes.json":{"n":["The Book of Hordes is a monster and military supplement created to streamline large-scale battles."],"a":["ATBOH"],"e":0},"Curio Solus; Festival Activies.json":{"n":["Festival Activities"],"a":["FESTiV"],"e":0},"Dave Eisinger; Discerning Merchant's Price Guide.json":{"n":["Discerning Merchant's Price Guide"],"a":["DMPG"],"e":0},"Dungeon Rollers; Ancestral Weapons.json":{"n":["Ancestral Weapons"],"a":["AnWe"],"e":0},"Ghostfire Gaming; Grim Hollow Campaign Guide.json":{"n":["Grim Hollow: The Campaign Guide (2014)"],"a":["GH:CG'14"],"e":0},"Ghostfire Gaming; Grim Hollow Player's Guide.json":{"n":["Grim Hollow: The Player's Guide (2014)"],"a":["GH:PG'14"],"e":0},"Ghostfire Gaming; Stibbles Codex of Companions.json":{"n":["Stibbles Codex of Companions"],"a":["SCoC"],"e":0},"Ghostfire Gaming; The Seeker's Guide to Twisted Taverns.json":{"n":["The Seeker's Guide to Twisted Taverns"],"a":["TSGtTT"],"e":0},"Goob the Goblin; A Guide for Warlocks, Mysteries of Magic.json":{"n":["A Guide For Warlocks, Mysteries Of Magic"],"a":["GfW:MoM"],"e":0},"Hipsters & Dragons; The White Scorpions Assassins Guild.json":{"n":["The White Scorpions Assassins Guild"],"a":["TWSAGU"],"e":0},"Jean Lorber; Knowledge is Power.json":{"n":["Knowledge is Power"],"a":["kip"],"e":0},"Justice Arman; Devil's Advocate A Guide to Infernal Contracts.json":{"n":["Devil's Advocate: A Guide to Infernal Contracts"],"a":["DA:GIC"],"e":0},"Loresmyth; Remarkable Inns & Their Drinks.json":{"n":["Remarkable Inns & Their Drinks"],"a":["RInD"],"e":0},"MCDM Productions; Kingdoms & Warfare.json":{"n":["Kingdoms & Warfare"],"a":["KaW"],"e":0},"Michael E Shea; Return of the Lazy Dungeon Master.json":{"n":["Return of the Lazy Dungeon Master"],"a":["RotLDM"],"e":0},"Raiders of the Serpent Sea; Player's Guide Free.json":{"n":["Raiders of the Serpent Sea: Player's Guide Free"],"a":["ROTSSPGF"],"e":0},"Russ Morrissey; Archery Contest.json":{"n":["Archery Contest"],"a":["Arch"],"e":0},"Saidoro; Sane Magic Item Prices.json":{"n":["Sane Magic Item Prices"],"a":["SMIP"],"e":0},"Skip Wiliams; Book of Challenges.json":{"n":["Book of Challenges: Dungeon Rooms, Puzzles, and Traps (3e)"],"a":["BoC🪤"],"e":0},"Walrock Homebrew; Fortresses, Temples, & Strongholds.json":{"n":["Fortresses, Temples, & Strongholds"],"a":["FT&S"],"e":0},"Walrock Homebrew; Teas and Tisanes.json":{"n":["Teas and Tisanes"],"a":["TT"],"e":0},"Walrock Homebrew; Traders and Merchants.json":{"n":["Traders And Merchants"],"a":["TaM"],"e":0},"Benjamin Huffman; Pugilist - 2024.json":{"n":["The Pugilist Class (2024)"],"a":["TPC'24"],"e":1},"Benjamin Huffman; Pugilist.json":{"n":["The Pugilist Class","Patreon Subclasses for the Pugilist"],"a":["SVM","SVMP"],"e":0},"Benjamin Huffman; The Magus.json":{"n":["The Magus Class"],"a":["BHM"],"e":0},"Ghostfire Gaming; Monster Hunter.json":{"n":["Monster Hunter"],"a":["MH"],"s":"wip","e":0},"Heavyarms; Gunslinger.json":{"n":["The Gunslinger Class","The Gunslinger Class - Unearthed Arcana: Class Feature Variants"],"a":["HA","UACFV"],"e":0},"KibblesTasty; Inventor.json":{"n":["KibblesTasty: Inventor"],"a":["KT:I"],"e":0},"KibblesTasty; Occultist.json":{"n":["KibblesTasty: Occultist"],"a":["KT:O"],"e":0},"KibblesTasty; Psion.json":{"n":["KibblesTasty: Psion"],"a":["KT:P"],"e":0},"KibblesTasty; Spellblade.json":{"n":["KibblesTasty: Spellblade"],"a":["KT:SB"],"e":0},"KibblesTasty; Warlord.json":{"n":["KibblesTasty: Warlord","KibblesTasty: Warlord Expanded Tactics"],"a":["KT:W","KT:WE"],"e":0},"LaserLlama; Alternate Artificer.json":{"n":["Alternate Artificer","Alternate Artificer Expanded"],"a":["LLAART","LLAART:E"],"e":0},"LaserLlama; Alternate Barbarian.json":{"n":["Alternate Barbarian","Alternate Barbarian Expanded"],"a":["LLAB","LLABE"],"e":0},"LaserLlama; Alternate Bard.json":{"n":["Alternate Bard"],"a":["LLABrd"],"e":0},"LaserLlama; Alternate Blood Hunter.json":{"n":["Alternate Blood Hunter"],"a":["LLABH"],"e":0},"LaserLlama; Alternate Druid.json":{"n":["Alternate Druid"],"a":["LLADru"],"e":0},"LaserLlama; Alternate Fighter.json":{"n":["Alternate Fighter","Alternate Fighter: Expanded"],"a":["LLAF","LLAF:E"],"e":0},"LaserLlama; Alternate Monk.json":{"n":["Alternate Monk","Alternate Monk Expanded"],"a":["LLAM","LLAM:E"],"e":0},"LaserLlama; Alternate Paladin.json":{"n":["Alternate Paladin"],"a":["LLAPal"],"e":0},"LaserLlama; Alternate Ranger.json":{"n":["Alternate Ranger","Alternate Ranger Expanded"],"a":["LLAR","LLAR:E"],"e":0},"LaserLlama; Alternate Rogue.json":{"n":["Alternate Rogue","Alternate Rogue Expanded"],"a":["LLARo","LLARoE"],"e":0},"LaserLlama; Alternate Sorcerer.json":{"n":["Alternate Sorcerer","Alternate Sorcerer: Expanded"],"a":["LLASorc","LLASorcorc:E"],"e":0},"LaserLlama; Alternate Warlock.json":{"n":["Alternate Warlock"],"a":["LLWrc"],"e":0},"LaserLlama; Alternate Wizard.json":{"n":["Alternate Wizard"],"a":["LLAWiz"],"e":0},"LaserLlama; Magus.json":{"n":["LaserLlama: Magus","LaserLlama: Magus Expended"],"a":["LLMag","LLMagE"],"e":0},"LaserLlama; Psion.json":{"n":["LaserLlama: Psion"],"a":["LLPs"],"e":0},"LaserLlama; Savant.json":{"n":["LaserLlama: Savant","LaserLlama: Savant Expanded"],"a":["LLSav","LLSavE"],"e":0},"LaserLlama; Shaman.json":{"n":["LaserLlama: Shaman","LaserLlama: Shaman Expanded"],"a":["LLSha","LLShaE"],"e":0},"LaserLlama; Vessel.json":{"n":["LaserLlama: Vessel"],"a":["LLVes"],"e":0},"LaserLlama; Warlord.json":{"n":["LaserLlama: Warlord","LaserLlama: Warlord Expanded"],"a":["LLWar","LLAWarE"],"e":0},"Loot Tavern; Gunner.json":{"n":["Zaman's Guide to the End of Time"],"a":["ZGttEoT"],"e":0},"Mage Hand Press; Complete Binder.json":{"n":["Mage Hand Press: Complete Binder"],"a":["MHP:CB"],"e":0},"Mage Hand Press; Gunslinger.json":{"n":["The Gunslinger Class: Valda's Spire of Secrets"],"a":["GC:VSS'24"],"p":1,"e":1},"Matthew Mercer; Blood Hunter (2022).json":{"n":["Blood Hunter 2022"],"a":["BH2022"],"e":0},"MCDM Productions; Beastheart.json":{"n":["Beastheart and Monstrous Companions"],"a":["BST"],"e":0},"MCDM Productions; The Illrigger Revised.json":{"n":["The Illrigger Revised"],"a":["IllR"],"p":1,"e":0},"Rain-Junkie; Dragon Knight.json":{"n":["Dragon Knight"],"a":["DK"],"e":0},"1985 Games; Obojima - Tales from the Tall Grass.json":{"n":["Obojima: Tales from the Tall Grass"],"a":["O:TTG"],"p":1,"e":0},"Alex Clippinger; Tome of the Pact.json":{"n":["Tome of the Pact"],"a":["TOEP"],"e":0},"Andrew Welker; Tasha's Crucible of Everything Else vol 2.json":{"n":["Tasha's Crucible of Everything Else - Volume 2"],"a":["TCEE2"],"e":0},"Arcanum Worlds; Odyssey of the Dragonlords Player's Guide.json":{"n":["Odyssey of the Dragonlords Player's Guide"],"a":["OotDLPG"],"e":0},"badooga; Badooga's Exploration Guidelines.json":{"n":["Badooga's Exploration Guidelines"],"a":["BEG"],"e":0},"badooga; Badooga's Monster Guidelines.json":{"n":["Badooga's Monster Guidelines"],"a":["BMG"],"e":0},"Benevolent Evil; The Elements and Beyond.json":{"n":["The Elements and Beyond","The Elements and Beyond: Spell Variants","The Elements and Beyond: Spell Revisions"],"a":["TEB","TEB","TEB"],"e":0},"Bonus Action; Bonus Action.json":{"n":["Bonus Action","Relics of the Realm Volume 1","Relics of the Realm Volume 2","Relics of the Realm Volume 3","Relics of the Realm Volume 4","Relics of the Realm Volume 5","Relics of the Realm Volume 6"],"a":["BA","RotR1","RotR2","RotR3","RotR4","RotR5","RotR6"],"e":0},"Community; Drakkenheim - Community Pack.json":{"n":["Drakkenheim: Community Pack"],"a":["Dk:CP"],"e":1},"DMs Guild; Archetypes of Eberron.json":{"n":["Archetypes of Eberron"],"a":["ArchEb"],"e":0},"DMsGuild; Xanathar's Lost Notes to Everything Else.json":{"n":["Xanathar's Lost Notes to Everything Else"],"a":["XLNEE"],"e":0},"Dungeon Dudes; Drakkenheim - Eldritch Experiments.json":{"n":["Drakkenheim: Eldritch Experiments (2014)","Drakkenheim: Eldritch Experiments (2024)"],"a":["Dk:EE'14","Dk:EE'24"],"e":1},"Dungeon Dudes; Sebastian Crowe's Guide to Drakkenheim.json":{"n":["Sebastian Crowe's Guide to Drakkenheim"],"a":["SCGtD"],"s":"wip","e":0},"EN Publishing; Level Up-Advanced 5th Edition Adventurer's Guide.json":{"n":["Level Up: Advanced 5th Edition Adventurer's Guide"],"a":["A5E:AG"],"e":0},"Genuine Fantasy Press; The Compendium of Forgotten Secrets - Awakening.json":{"n":["The Compendium of Forgotten Secrets: Awakening"],"a":["CoFS:A"],"e":0},"Ghostfire Gaming; Dungeons of Drakkenheim.json":{"n":["Dungeons of Drakkenheim"],"a":["DoDk"],"p":1,"e":0},"Ghostfire Gaming; Grim Hollow - Lairs of Etharis.json":{"n":["Grim Hollow: Lairs of Etharis"],"a":["GHLoE"],"p":1,"e":0},"Ghostfire Gaming; Grim Hollow - Player Pack.json":{"n":["Grim Hollow: Player Pack"],"a":["GH:PP"],"p":1,"e":0},"Ghostfire Gaming; Grim Hollow - Player's Guide - 2024.json":{"n":["Grim Hollow: Player's Guide (2024)"],"a":["GH:PG'24"],"p":1,"e":1},"Ghostfire Gaming; Grim Hollow - The Monster Grimoire.json":{"n":["Grim Hollow: The Monster Grimoire"],"a":["GHMG"],"e":0},"Ghostfire Gaming; Monsters of Drakkenheim.json":{"n":["Monsters of Drakkenheim"],"a":["MoDk"],"p":1,"e":1},"Ghostfire Gaming; Sebastian Crowe's Guide to Drakkenheim.json":{"n":["Sebastian Crowe's Guide to Drakkenheim"],"a":["SCGtD"],"e":0},"Griffin Macaulay; The Griffon's Saddlebag, Book 1.json":{"n":["The Griffon's Saddlebag, Book 1"],"a":["TGS1"],"e":0},"Griffin Macaulay; The Griffon's Saddlebag, Book 2.json":{"n":["The Griffon's Saddlebag, Book 2"],"a":["TGS2"],"p":1,"e":0},"Griffin Macaulay; The Griffon's Saddlebag, Book 3.json":{"n":["The Griffon's Saddlebag, Book 3"],"a":["TGS3"],"e":0},"Griffin Macaulay; The Griffon's Saddlebag, Book 4.json":{"n":["The Griffon's Saddlebag, Book 4"],"a":["TGS4"],"e":0},"Griffin Macaulay; The Griffon's Saddlebag, Book 5.json":{"n":["The Griffon's Saddlebag, Book 5"],"a":["TGS5"],"e":0},"Heavyarms; The Complete Armorer's Handbook.json":{"n":["The Complete Armorer's Handbook"],"a":["TCAH"],"e":0},"Hit Point Press; Humblewood Campaign Setting.json":{"n":["Humblewood Campaign Setting"],"a":["HWCS"],"p":1,"e":0},"Hit Point Press; Humblewood Tales.json":{"n":["Humblewood Tales"],"a":["HWT"],"p":1,"e":0},"Jeremy Forbing; Elminsters Guide to Magic.json":{"n":["Elminsters Guide to Magic v3"],"a":["EGM"],"e":0},"Jonoman3000; Blazing Dawn Player's Companion.json":{"n":["Blazing Dawn Player's Companion"],"a":["BDPC"],"e":0},"Jonoman3000; Dark Arts Players Companion.json":{"n":["Dark Arts Player's Companion"],"a":["DAPC"],"e":0},"Jonoman3000; Sprouting Chaos Player's Companion.json":{"n":["Sprouting Chaos Player's Companion"],"a":["SCPC"],"e":0},"Keith Baker; Chronicles of Eberron.json":{"n":["Chronicles of Eberron"],"a":["CoE"],"e":0},"Keith Baker; Dread Metrol - Into the Mists.json":{"n":["Dread Metrol: Into the Mists"],"a":["DMIM"],"s":"wip","e":0},"Keith Baker; Exploring Eberron.json":{"n":["Exploring Eberron"],"a":["ExE"],"e":0},"Keith Baker; Frontiers of Eberron Quickstone.json":{"n":["Frontiers of Eberron: Quickstone"],"a":["FoEQ"],"s":"wip","e":1},"Keith Baker; Morgrave Miscellany.json":{"n":["Morgrave Miscellany"],"a":["MoMi"],"e":0},"KibblesTasty; Kibbles' Compendium of Legends and Legacies.json":{"n":["Kibbles' Compendium of Legends and Legacies","The Arena Guy, Spectre Creations"],"a":["KCLL","TAG"],"e":0},"KibblesTasty; Kibbles' Crafting Guide.json":{"n":["KibblesTasty: Kibbles' Crafting Guide"],"a":["KT: KCG"],"e":0},"Kobold Press; Book of Ebon Tides.json":{"n":["Book of Ebon Tides"],"a":["BoET"],"p":1,"e":0},"Kobold Press; Tales from the Shadows.json":{"n":["Tales from the Shadows"],"a":["TftS"],"p":1,"e":0},"Kobold Press; Tome of Heroes.json":{"n":["Tome of Heroes"],"a":["ToH"],"e":0},"Loot Tavern; Heliana's Guide To Monster Hunting.json":{"n":["Heliana's Guide to Monster Hunting"],"a":["HGtMH"],"e":0},"Loot Tavern; Ryoko's Guide to Yokai Realms.json":{"n":["Ryoko's Guide to the Yokai Realms"],"a":["RGTYR"],"e":0},"Loot Tavern; Wrath of the Kaijus.json":{"n":["Wrath of the Kaiju"],"a":["WOTK"],"e":0},"Mage Hand Press; Dark Matter - 2024.json":{"n":["Dark Matter (2024)"],"a":["DM'24"],"e":1},"Mage Hand Press; Dark Matter.json":{"n":["Dark Matter (2014)","Dark Matter Extras (2014)"],"a":["DM'14","DM'14+"],"e":0},"Mage Hand Press; Valda Spire of Secrets - 2024.json":{"n":["Valda's Spire of Secrets (2024)","The Alchemist Class: Valda's Spire of Secrets (2024)","The Captain Class: Valda's Spire of Secrets (2024)","The Craftsman Class: Valda's Spire of Secrets (2024)","The Witch Class: Valda's Spire of Secrets (2024)","The Necromancer Class: Valda's Spire of Secrets (2024)","The Martyr Class: Valda's Spire of Secrets (2024)","The Investigator Class: Valda's Spire of Secrets (2024)","The Vagabond Class: Valda's Spire of Secrets (2024)","The Warmage Class: Valda's Spire of Secrets (2024)","The Warden Class: Valda's Spire of Secrets (2024)"],"a":["VSS'24","AC:VSS'24","CC:VSS'24","CMC:VSS'24","WC:VSS'24","NC:VSS'24","MC:VSS'24","IC:VSS'24","VC:VSS'24","WMC:VSS'24","WDC:VSS'24"],"e":1},"Mage Hand Press; Valda's Spire of Secrets - Player Pack.json":{"n":["Valda's Spire of Secrets: Player Pack"],"a":["VSS:PP"],"p":1,"e":1},"Mage Hand Press; Valda's Spire of Secrets.json":{"n":["Valda's Spire of Secrets (2014)","Valda's Spire of Secrets Extras (2014)"],"a":["VSS'14","VSS'14+"],"e":0},"MCDM Productions; Strongholds and Followers.json":{"n":["Strongholds and Followers"],"a":["S&F"],"e":0},"MCDM Productions; Where Evil Lives.json":{"n":["Where Evil Lives: The MCDM Book of Boss Battles"],"a":["WEL"],"p":1,"e":0},"MonkeyDM; Dark Tides of Bilgewater - Rebalanced.json":{"n":["Legends of Runeterra: Dark Tides of Bilgewater - Rebalanced"],"a":["DToB:R"],"e":0},"MonkeyDM; Northern Lights Compendium.json":{"n":["Northern Lights Compendium"],"a":["NLC"],"e":0},"MonkeyDM; Steinhardt's Guide to the Eldritch Hunt.json":{"n":["Steinhardt's Guide to the Eldritch Hunt"],"a":["SGttEH"],"e":0},"Nord Games; Game Master's Toolbox Ultimate NPCs Skulduggery.json":{"n":["Game Master's Toolbox: Ultimate NPCs: Skulduggery"],"a":["GMT:S"],"e":0},"Nord Games; Treacherous Traps.json":{"n":["Treacherous Traps"],"a":["TreTra"],"s":"wip","e":0},"Plus Three Press; Crystalpunk Campaign Guide.json":{"n":["Crystalpunk Campaign Guide"],"a":["CCG"],"e":0},"QL Games; Tasha's Crucible of Everything Else - Volume 1.json":{"n":["Tasha's Crucible of Everything Else - Volume 1"],"a":["TCEE1"],"e":0},"Sterling Vermin Adventuring Co.; The Ultimate Adventurer's Handbook.json":{"n":["The Ultimate Adventurer's Handbook"],"a":["UAH"],"e":0},"Anthony Turco; Korranberg Chronicle's Threat Dispatch.json":{"n":["Korranberg Chronicle's Threat Dispatch"],"a":["KCTD"],"e":0},"Anthony Turco; Nightmare on the Mournland Express.json":{"n":["Nightmare on the Mournland Express"],"a":["NotME"],"e":0},"badooga; Better Greatwyrms.json":{"n":["Better Greatwyrms"],"a":["BeGr"],"e":0},"Glen Cooper; Monsters of the Guild.json":{"n":["Monsters of the Guild"],"a":["MotG"],"e":0},"Kobold Press; Creature Codex.json":{"n":["Creature Codex"],"a":["CCodex"],"e":0},"Kobold Press; Gem Dragons of Faerun.json":{"n":["Gem Dragons of Faerûn"],"a":["GDoF"],"e":0},"Kobold Press; Tome of Beasts 1 (2023 Edition).json":{"n":["Tome of Beasts 1 (2023 Edition)"],"a":["ToB1'23"],"p":1,"e":0},"Kobold Press; Tome of Beasts 2.json":{"n":["Tome of Beasts 2"],"a":["ToB2"],"e":0},"Kobold Press; Tome of Beasts 3.json":{"n":["Tome of Beasts 3"],"a":["ToB3"],"e":0},"Lair of Dragons; 5 High Level Villains.json":{"n":["5 High Level Villains"],"a":["LOD5HLV"],"e":0},"Lair of Dragons; 5 Low Level Villains.json":{"n":["5 Low Level Villains"],"a":["5LLV"],"e":0},"LaserLlama; Compendium of Beasts.json":{"n":["Compendium of Beasts"],"a":["LLCoB"],"e":1},"MCDM Productions; Flee, Mortals!.json":{"n":["Flee, Mortals!"],"a":["FM!"],"p":1,"e":0},"Mistfactor Press; Darklords & Domains.json":{"n":["Mistfactor Press - Darklords & Domains"],"a":["MPDAD"],"e":0},"Mythos Chronicles; Mythological Creatures.json":{"n":["Mythological Creatures"],"a":["MyC"],"e":0},"Nicksoliss; The Seven Dragon Overlords.json":{"n":["The Seven Dragon Overlords"],"a":["NS_TSDO"],"e":0},"Palaeo Games; Dr Dhrolins Dictionary of Dinosaurs.json":{"n":["Dr Dhrolin's Dictionary of Dinosaurs"],"a":["DDDD"],"e":0},"World Builder Blog; Catastrophic Dragons.json":{"n":["Catastrophic Dragons"],"a":["WBBCD"],"e":0},"WotC; Keys from the Golden Vault - Calling Cards.json":{"n":["Keys from the Golden Vault: Calling Cards"],"a":["KftGV:CC"],"e":0},"DnD Beyond; Expanded Racial Feats.json":{"n":["D&D Beyond"],"a":["Bnd"],"e":0},"KibblesTasty; Feats for Faiths.json":{"n":["Feats for Faiths"],"a":["KTFfF"],"e":0},"KibblesTasty; Kibbles' Active Martial Feats.json":{"n":["Active Martial Feats"],"a":["KT:AMF"],"e":0},"ArcanaGames; Visions of the Vault.json":{"n":["Visions of the Vault"],"a":["VotV"],"e":0},"ArmedPirate; Hoard of Kryx the Dragon.json":{"n":["Hoard of Kryx the Dragon"],"a":["HKD"],"e":0},"DMsGuild Community; Artifacts of the Guild.json":{"n":["Artifacts of the Guild"],"a":["AotG"],"e":0},"griff-mac; The Griffon's Saddlebag.json":{"n":["The Griffon's Saddlebag"],"a":["TGS"],"s":"deprecated","e":0},"Mythos Chronicles; Mythological Items.json":{"n":["Mythological Items"],"a":["MyI"],"s":"wip","e":0},"Yonael; Firearms of the Realm.json":{"n":["Firearms of The Realms"],"a":["FoTR"],"e":0},"laserllama; Laserllama's Exploit Compendium.json":{"n":["LaserLlama's Exploit Compendium"],"a":["LLExploits"],"e":0},"Benjamin Huffman; Beastfolk.json":{"n":["Beastfolk"],"a":["BF"],"e":0},"IronRule; Epic Boons.json":{"n":["Epic Boons"],"a":["EpicBoons"],"e":0},"Jessica Wolfman; The (Not Really) Complete Tome of Spells.json":{"n":["The (Not Really) Complete Tome of Spells"],"a":["NRCToS"],"e":0},"KibblesTasty; Kibbles' Casting Compendium.json":{"n":["Kibbles' Casting Compendium","Kibbles' Blood Magic Spells"],"a":["KCC","KBMS"],"e":0},"KibblesTasty; Kibbles' Generic Elemental Spells.json":{"n":["Kibbles' Generic Elemental Spells"],"a":["KGES"],"e":0},"KibblesTasty; Summoning Spells.json":{"n":["Summoning Spells (by KibblesTasty)"],"a":["KTSS"],"e":0},"LaserLlama; LaserLlama's Compendium of Spells.json":{"n":["Laserllama: Compendium of Spells"],"a":["LLCS"],"e":1},"Matthew Mercer; Widogast's Web of Fire.json":{"n":["Widowgast's Web of Fire"],"a":["WWoF"],"e":0},"somanyrobots, Omega Ankh; Spells That Don't Suck.json":{"n":["Spells That Don't Suck"],"a":["STDS"],"e":1},"somanyrobots; So Many Spells.json":{"n":["So Many Spells"],"a":["SMS"],"e":0},"SwEcky; Spells by SwEcky.json":{"n":["Spells by SwEcky"],"a":["SbSwE"],"e":0},"Ark1002; Order of the Revenant.json":{"n":["Order of the Revenant"],"a":["BH:OftR"],"e":0},"Ghostfire Gaming; Artificer Subclasses.json":{"n":["Artificer Subclasses - A Dark Fantasy Supplement"],"a":["AS:DFS"],"e":0},"KibblesTasty; Divine Agent.json":{"n":["Divine Agent"],"a":["DivAgen"],"e":0},"KibblesTasty; Path of the Bladestorm.json":{"n":["Path of the Bladestorm"],"a":["PotB"],"e":0},"Kingstarman; Way of the Cherry Blossom Sage.json":{"n":["Way of the Cherry Blossom Sage"],"a":["CBS"],"e":0},"LaserLlama; Alternate Barbarian Path of the Blood Knight.json":{"n":["Path of the Blood Knight"],"a":["LLABBK"],"s":"wip","e":0},"Laserllama; Artificer Specialties & Infusion Options.json":{"n":["LaserLlama's Artificer Specialties & Infusion Options"],"a":["LL:AS&IO"],"e":0},"LaserLlama; Bard Colleges.json":{"n":["LaserLlama's Bard Colleges"],"a":["LL:BC"],"e":0},"LaserLlama; Druid Circles.json":{"n":["Druid Circles"],"a":["LL:DC"],"e":0},"LaserLlama; Fighter Archetypes & Fighting Styles.json":{"n":["LaserLlama's Fighter Archetypes & Fighting Styles"],"a":["LLFAFS"],"e":0},"LaserLlama; Monastic Traditions.json":{"n":["LaserLlama's Monastic Traditions"],"a":["LLMT"],"e":0},"LaserLlama; Otherwordly Patrons.json":{"n":["Otherworldy Patrons: Eleven new Otherworldly Patrons for the Warlock Class in the World's Greatest Roleplaying Game"],"a":["OWP"],"e":0},"LaserLlama; Paladin Sacred Oaths.json":{"n":["Paladin Sacred Oaths"],"a":["LLPSO"],"e":0},"LaserLlama; Primal Paths.json":{"n":["LaserLlama's Primal Paths"],"a":["LL:PP"],"e":0},"Laserllama; Roguish Archetypes.json":{"n":["Laserllama's Roguish Archetypes"],"a":["LL:RA"],"e":0},"Loot Tavern Publishing; Spirit Caller.json":{"n":["Ryoko's Guide - Spirit Caller (Playtest)"],"a":["RGSC"],"s":"wip","e":0},"Mage Hand Press; Gunslinger Extras.json":{"n":["The Gunslinger Class: Valda's Spire of Secrets (Extras)"],"a":["GC:VSS'24+"],"e":1},"Mage Hand Press; The Toon Warlock Patron.json":{"n":["The Toon Otherworldly Patron"],"a":["MFOV:TT"],"e":0},"Matthew Mercer; College of the Maestro.json":{"n":["College of the Maestro"],"a":["CR"],"e":0},"Matthew Mercer; Oath of the Open Sea.json":{"n":["Oath of the Open Sea"],"a":["OoOS"],"e":0},"Matthew Mercer; Way of the Cobalt Soul.json":{"n":["Way of the Cobalt Soul"],"a":["WotCS"],"e":0},"MonkeyDM; Artificer Mortis Engineer.json":{"n":["Steinhardt's Guide to the Eldritch Hunt: Artificer Mortis Engineer"],"a":["SGttEH:AME"],"e":0},"MonkeyDM; Oath of the Eldritch Hunt.json":{"n":["Oath of the Eldritch Hunt"],"a":["OEH"],"e":0},"MonkeyDM; Pact of the trigger.json":{"n":["Pact of the trigger"],"a":["MDMPOTT"],"e":0},"somanyrobots; Rimeblade.json":{"n":["Rimeblade"],"a":["Unearthed Arcana - Reddit"],"e":0},"somanyrobots; The Agitator.json":{"n":["The Agitator"],"a":["Unearthed Arcana - Reddit"],"e":0},"somanyrobots; The Firestarter.json":{"n":["The Firestarter"],"a":["Unearthed Arcana - Reddit"],"e":0},"somanyrobots; Way of Predation.json":{"n":["Way of Predation"],"a":["Unearthed Arcana - Reddit"],"e":0},"Raging Swan; Tables.json":{"n":["Raging Swan Press"],"a":["RSP"],"e":0},"James Introcaso; 20 New Traps.json":{"n":["20 New Traps"],"a":["20NT"],"e":0},"blainesilver; (More Predictible) Wish Spells.json":{"n":["(More Predictible) Wish Spells"],"a":["MPWS"],"e":0},"Dael Kingsmill; Thieves' Cant.json":{"n":["Thieves' Cant"],"a":["MF:TC"],"e":0},"Matthew Mercer; Corruption Rules.json":{"n":["Corruption Rules by Matthew Mercer"],"a":["MM:CR"],"e":0}}